README.md
setup.py
HashDL/__init__.py
HashDL/activation.hh
HashDL/data.hh
HashDL/hash.hh
HashDL/hashdl.cpp
HashDL/hashdl.pyx
HashDL/initializer.hh
HashDL/optimizer.hh
HashDL/scheduler.hh
HashDL/slide.hh
HashDL/slide.pxd
HashDL.egg-info/PKG-INFO
HashDL.egg-info/SOURCES.txt
HashDL.egg-info/dependency_links.txt
HashDL.egg-info/requires.txt
HashDL.egg-info/top_level.txt
test/test_HashDL.py